zolltools/__init__.py
zolltools/logging.py
zolltools/pqtools.py
zolltools/sasconvert.py
zolltools-0.2.dist-info/METADATA
zolltools-0.2.dist-info/WHEEL
zolltools-0.2.dist-info/licenses/LICENSE
zolltools-0.2.dist-info/RECORD
