Metadata-Version: 2.1
Name: zolltools
Version: 0.2
Summary: A collection of tools for working with NEMSIS data
Project-URL: Homepage, https://github.com/Jython1415/zolltools
Project-URL: Bug Tracker, https://github.com/Jython1415/zolltools/issues
Author-email: Joshua Shew <joshua.t.shew@gmail.com>
License-File: LICENSE
Classifier: Development Status :: 4 - Beta
Classifier: Intended Audience :: Developers
Classifier: Intended Audience :: Healthcare Industry
Classifier: Intended Audience :: Science/Research
Classifier: License :: OSI Approved :: MIT License
Classifier: Operating System :: OS Independent
Classifier: Programming Language :: Python :: 3
Classifier: Topic :: Scientific/Engineering :: Medical Science Apps.
Requires-Python: >=3.9
Requires-Dist: fastparquet>2023.1.0
Requires-Dist: pandas>=0.4
Requires-Dist: pyarrow>=2
Requires-Dist: pyreadstat>=1.1.7
